{
  "books": [
    {
      "id" : 0,
      "title" : "Harry Potter i Kamień Filozoficzny",
      "author" : "J.K. Rowling",
      "pages" : "328",
      "released" : "2016-07-20",
      "publishingHouse" : "Media Rodzina",
      "genre" : "literatura młodzieżowa",
      "rating" : "8.1",
      "numberOfRatings" : "78479",
      "translator" : "Andrzej Polkowski",
      "price" : "21.12",
      "picture" : ""
    },
    {
      "id" : 1,
      "title" : "Mały Książę. Wydanie ekskluzywne",
      "author" : "Antoine de Saint-Exupéry",
      "pages" : "80",
      "released" : "2020-10-12",
      "publishingHouse" : "Wydawnictwo SBM",
      "genre" : "literatura piekna",
      "rating" : "7.9",
      "numberOfRatings" : "58693",
      "translator" : "Martyna M. Lemańczyk",
      "price" : "17.83",
      "picture" : ""
    },
    {
      "id" : 2,
      "title" : "Lata",
      "author" : "Annie Ernaux",
      "pages" : "240",
      "released" : "2022-01-12",
      "publishingHouse" : "Czarne",
      "genre" : "literatura piękna",
      "rating" : "7.4",
      "numberOfRatings" : "308",
      "translator" : "Krzysztof Jarosz, Magdalena Budzińska",
      "price" : "22.52",
      "picture" : "https://s.lubimyczytac.pl/upload/books/4992000/4992460/1021144-352x500.jpg"
    },
    {
      "id" : 3,
      "title" : "Mistrz i Małgorzata",
      "author" : "Michaił Bułhakow",
      "pages" : "544",
      "released" : "2022-03-23",
      "publishingHouse" : "Świat Książki",
      "genre" : "klasyka",
      "rating" : "8.4",
      "numberOfRatings" : "48430",
      "translator" : "brak danych",
      "price" : "11.69",
      "picture" : "https://s.lubimyczytac.pl/upload/books/5001000/5001198/958056-352x500.jpg"
    },
    {
      "id" : 4,
      "title" : "Igrzyska śmierci",
      "author" : "Suzanne Collins",
      "pages" : "378",
      "released" : "2018-10-17",
      "publishingHouse" : "Media Rodzina",
      "genre" : "literatura młodzieżowa",
      "rating" : "8.2",
      "numberOfRatings" : "43566",
      "translator" : "Małgorzata Hesko-Kołodzińska, Piotr Budkiewicz",
      "price" : "7.30",
      "picture" : "https://s.lubimyczytac.pl/upload/books/4862000/4862898/690923-352x500.jpg"
    },
    {
      "id" : 5,
      "title" : "Rok 1984",
      "author" : "George Orwell",
      "pages" : "352",
      "released" : "2022-04-05",
      "publishingHouse" : "Rebis",
      "genre" : "fantasy, science fiction",
      "rating" : "8.5",
      "numberOfRatings" : "43800",
      "translator" : "Andrzej Jankowski",
      "price" : "21.12",
      "picture" : ""
    },
    {
      "id" : 6,
      "title" : "Harry Potter i Kamień Filozoficzny",
      "author" : "J.K. Rowling",
      "pages" : "328",
      "released" : "1997-01-01",
      "publishingHouse" : "Media Rodzina",
      "genre" : "literatura młodzieżowa",
      "rating" : "8.1",
      "numberOfRatings" : "78479",
      "translator" : "Andrzej Polkowski",
      "price" : "21.12",
      "picture" : ""
    },
    {
      "id" : 7,
      "title" : "Harry Potter i Kamień Filozoficzny",
      "author" : "J.K. Rowling",
      "pages" : "328",
      "released" : "1997-01-01",
      "publishingHouse" : "Media Rodzina",
      "genre" : "literatura młodzieżowa",
      "rating" : "8.1",
      "numberOfRatings" : "78479",
      "translator" : "Andrzej Polkowski",
      "price" : "21.12",
      "picture" : ""
    },
    {
      "id" : 8,
      "title" : "Harry Potter i Kamień Filozoficzny",
      "author" : "J.K. Rowling",
      "pages" : "328",
      "released" : "1997-01-01",
      "publishingHouse" : "Media Rodzina",
      "genre" : "literatura młodzieżowa",
      "rating" : "8.1",
      "numberOfRatings" : "78479",
      "translator" : "Andrzej Polkowski",
      "price" : "21.12",
      "picture" : ""
    },
    {
      "id" : 9,
      "title" : "Harry Potter i Kamień Filozoficzny",
      "author" : "J.K. Rowling",
      "pages" : "328",
      "released" : "1997-01-01",
      "publishingHouse" : "Media Rodzina",
      "genre" : "literatura młodzieżowa",
      "rating" : "8.1",
      "numberOfRatings" : "78479",
      "translator" : "Andrzej Polkowski",
      "price" : "21.12",
      "picture" : ""
    }
  ]
}